django_busybody/__init__.py
django_busybody/admin.py
django_busybody/apps.py
django_busybody/datas.py
django_busybody/decorators.py
django_busybody/easy_crypto.py
django_busybody/middlewares.py
django_busybody/models.py
django_busybody/rules.py
django_busybody/tools.py
django_busybody/urls.py
django_busybody/validators.py
django_busybody/views.py
django_busybody/custom_backends/__init__.py
django_busybody/custom_backends/mail_bcc.py
django_busybody/custom_backends/mail_hook.py
django_busybody/custom_backends/mail_logger.py
django_busybody/custom_storages/__init__.py
django_busybody/custom_storages/chain.py
django_busybody/custom_storages/hashed.py
django_busybody/custom_storages/overwrite.py
django_busybody/custom_storages/s3.py
django_busybody/management/__init__.py
django_busybody/management/commands/__init__.py
django_busybody/migrations/0001_initial.py
django_busybody/migrations/0002_auto_20170513_0809.py
django_busybody/migrations/0003_emaillog_from_email.py
django_busybody/migrations/0004_auto_20170516_0841.py
django_busybody/migrations/0005_naivelock.py
django_busybody/migrations/0006_emaillog_user_id.py
django_busybody/migrations/__init__.py
django_busybody/static/css/django_busybody.css
django_busybody/static/js/django_busybody.js
django_busybody/templates/busybody/base.html
django_busybody/templates/busybody/snippets/paging.html
django_busybody/templatetags/__init__.py
django_busybody/templatetags/busybody.py
django_busybody-0.2.1.dist-info/DESCRIPTION.rst
django_busybody-0.2.1.dist-info/METADATA
django_busybody-0.2.1.dist-info/RECORD
django_busybody-0.2.1.dist-info/WHEEL
django_busybody-0.2.1.dist-info/metadata.json
django_busybody-0.2.1.dist-info/top_level.txt
