Metadata-Version: 2.0
Name: django-busybody
Version: 0.2.1
Summary: django misc
Home-page: https://github.com/s1s5/django_busybody
Author: Shogo Sawai
Author-email: shogo.sawai@gmail.com
License: MIT
Keywords: django_busybody
Platform: UNKNOWN
Classifier: Development Status :: 3 - Alpha
Classifier: Framework :: Django
Classifier: Framework :: Django :: 1.10
Classifier: Intended Audience :: Developers
Classifier: License :: OSI Approved :: BSD License
Classifier: Natural Language :: English
Classifier: Programming Language :: Python :: 2
Classifier: Programming Language :: Python :: 2.7
Classifier: Programming Language :: Python :: 3
Classifier: Programming Language :: Python :: 3.4
Classifier: Programming Language :: Python :: 3.5
